Metadata-Version: 2.1
Name: odoo12-addon-base-search-fuzzy
Version: 12.0.1.0.2
Summary: Fuzzy search with the PostgreSQL trigram extension
Home-page: https://github.com/OCA/server-tools
Author: bloopark systems GmbH & Co. KG, Eficent, Serpent CS, Odoo Community Association (OCA)
Author-email: support@odoo-community.org
License: AGPL-3
Platform: UNKNOWN
Classifier: Programming Language :: Python
Classifier: Framework :: Odoo
Classifier: License :: OSI Approved :: GNU Affero General Public License v3
Requires-Python: >=3.5
Requires-Dist: odoo (<12.1dev,>=12.0a)
